{
    "version": "20210430.0.61619",
    "architecture": {
        "64bit": {
            "url": "https://github.com/kopia/kopia-test-builds/releases/download/v20210430.0.61619/kopia-20210430.0.61619-windows-x64.zip",
            "bin": [
                "kopia-20210430.0.61619-windows-x64/kopia.exe"
            ],
            "hash": "d678c8a1b701fdb36f84bd277a1ebf3cddf2438c24c01ef1ae2e6ac363a9a838"
        }
    },
    "homepage": "https://kopia.io/",
    "license": "Apache-2.0",
    "description": "Fast and secure open source backup."
}