{
    "version": "20211002.0.125608",
    "architecture": {
        "64bit": {
            "url": "https://github.com/kopia/kopia-test-builds/releases/download/v20211002.0.125608/kopia-20211002.0.125608-windows-x64.zip",
            "bin": [
                "kopia-20211002.0.125608-windows-x64/kopia.exe"
            ],
            "hash": "8ee33a8ec8ed14c421e8971b72ecc49aea050d4523bafb4056c82dca034d0eea"
        }
    },
    "homepage": "https://kopia.io/",
    "license": "Apache-2.0",
    "description": "Fast and secure open source backup."
}