{
    "version": "20220904.0.210215",
    "description": "Fast and secure open source backup.",
    "homepage": "https://kopia.io/",
    "license": "Apache-2.0",
    "architecture": {
        "64bit": {
            "url": "https://github.com/kopia/kopia-test-builds/releases/download/v20220904.0.210215/kopia-20220904.0.210215-windows-x64.zip",
            "bin": [
                "kopia.exe"
            ],
            "hash": "94cc5eca1ed8125e28a6bed62d743a5d2ffbf656d922cb5a6a6d2267fa89715b",
            "extract_dir": "kopia-20220904.0.210215-windows-x64"
        }
    }
}
