{
    "version": "20260203.0.52605",
    "description": "Fast and secure open source backup.",
    "homepage": "https://kopia.io/",
    "license": "Apache-2.0",
    "architecture": {
        "64bit": {
            "url": "https://github.com/kopia/kopia-test-builds/releases/download/v20260203.0.52605/kopia-20260203.0.52605-windows-x64.zip",
            "bin": [
                "kopia.exe"
            ],
            "hash": "1b5cabb99b2ec0d3d52e542f21a1d1650fd29f283263c9e9fdb87b4861d03473",
            "extract_dir": "kopia-20260203.0.52605-windows-x64"
        }
    }
}
