{
    "version": "20211106.0.230800",
    "description": "Fast and secure open source backup.",
    "homepage": "https://kopia.io/",
    "license": "Apache-2.0",
    "architecture": {
        "64bit": {
            "url": "https://github.com/kopia/kopia-test-builds/releases/download/v20211106.0.230800/kopia-20211106.0.230800-windows-x64.zip",
            "bin": [
                "kopia.exe"
            ],
            "hash": "e5c8915b0a8706ca69bc9a2904ed59c1965931d101cb035d26f95212bef020af",
            "extract_dir": "kopia-20211106.0.230800-windows-x64"
        }
    }
}
