{
    "version": "20220706.0.55427",
    "description": "Fast and secure open source backup.",
    "homepage": "https://kopia.io/",
    "license": "Apache-2.0",
    "architecture": {
        "64bit": {
            "url": "https://github.com/kopia/kopia-test-builds/releases/download/v20220706.0.55427/kopia-20220706.0.55427-windows-x64.zip",
            "bin": [
                "kopia.exe"
            ],
            "hash": "4e304d1a0f8c852bba9a23cece15937163c91f046c3c87eb2c4efd28dc9fc0f4",
            "extract_dir": "kopia-20220706.0.55427-windows-x64"
        }
    }
}
