{
    "version": "20260206.0.181501",
    "description": "Fast and secure open source backup.",
    "homepage": "https://kopia.io/",
    "license": "Apache-2.0",
    "architecture": {
        "64bit": {
            "url": "https://github.com/kopia/kopia-test-builds/releases/download/v20260206.0.181501/kopia-20260206.0.181501-windows-x64.zip",
            "bin": [
                "kopia.exe"
            ],
            "hash": "c8fdfcb5feb57292e2951028c6d0a685af29d41ab1b3e049d9fbee914655b601",
            "extract_dir": "kopia-20260206.0.181501-windows-x64"
        }
    }
}
